LICENSE
MANIFEST.in
README.rst
VERSION
setup.cfg
setup.py
versionalchemy/__init__.py
versionalchemy/exceptions.py
versionalchemy/utils.py
versionalchemy.egg-info/PKG-INFO
versionalchemy.egg-info/SOURCES.txt
versionalchemy.egg-info/dependency_links.txt
versionalchemy.egg-info/requires.txt
versionalchemy.egg-info/top_level.txt
versionalchemy/api/__init__.py
versionalchemy/api/data.py
versionalchemy/models/__init__.py